{"retweeted":false,"source":"<a href=\"http://twitter.com\" rel=\"nofollow\">Twitter Web Client</a>","entities":{"hashtags":[],"symbols":[],"user_mentions":[],"urls":[{"url":"https://t.co/XVuyWmu2MQ","expanded_url":"https://www.kickstarter.com/projects/688524040/slumberpod-portable-privacy-pod-for-babies-and-tod?ref=531394&token=40559ac2","display_url":"kickstarter.com/projects/68852…","indices":["84","107"]}]},"display_text_range":["0","107"],"favorite_count":"22","id_str":"1021799700092018688","truncated":false,"retweet_count":"3","id":"1021799700092018688","possibly_sensitive":false,"created_at":"Tue Jul 24 16:50:07 +0000 2018","favorited":false,"full_text":"If you are a parent who travels with a kid. My friend is making something for you.\n\nhttps://t.co/XVuyWmu2MQ","lang":"en"}