{"retweeted":false,"source":"<a href=\"http://twitter.com\" rel=\"nofollow\">Twitter Web Client</a>","entities":{"hashtags":[],"symbols":[],"user_mentions":[],"urls":[{"url":"https://t.co/TgasGgVCov","expanded_url":"https://giant.gfycat.com/UnluckySameKinglet.gif","display_url":"giant.gfycat.com/UnluckySameKin…","indices":["78","101"]}]},"display_text_range":["0","101"],"favorite_count":"8","id_str":"677188201895751680","truncated":false,"retweet_count":"4","id":"677188201895751680","possibly_sensitive":false,"created_at":"Wed Dec 16 18:07:03 +0000 2015","favorited":false,"full_text":"The Minecraft generation of directors is on the way (this is minecraft, fyi)  https://t.co/TgasGgVCov","lang":"en"}