{"retweeted":false,"source":"<a href=\"http://twitter.com\" rel=\"nofollow\">Twitter Web Client</a>","entities":{"hashtags":[],"symbols":[],"user_mentions":[],"urls":[]},"display_text_range":["0","130"],"favorite_count":"2","id_str":"362208674854346755","truncated":false,"retweet_count":"0","id":"362208674854346755","created_at":"Tue Jul 30 13:50:52 +0000 2013","favorited":false,"full_text":"Would you fly in an airplane if you had built every part? If not, what does that say about your opinion of your own craftsmanship?","lang":"en"}