{"retweeted":false,"source":"<a href=\"http://twitter.com\" rel=\"nofollow\">Twitter Web Client</a>","entities":{"hashtags":[],"symbols":[],"user_mentions":[{"name":"Greg Wester","screen_name":"gwestr","indices":["0","7"],"id_str":"254873442","id":"254873442"}],"urls":[]},"display_text_range":["0","21"],"favorite_count":"0","in_reply_to_status_id_str":"664213874053287936","id_str":"664216570462244864","in_reply_to_user_id":"254873442","truncated":false,"retweet_count":"0","id":"664216570462244864","in_reply_to_status_id":"664213874053287936","created_at":"Tue Nov 10 23:02:25 +0000 2015","favorited":false,"full_text":"@gwestr hey, too soon","lang":"en","in_reply_to_screen_name":"gwestr","in_reply_to_user_id_str":"254873442"}