{"retweeted":false,"source":"<a href=\"http://twitter.com\" rel=\"nofollow\">Twitter Web Client</a>","entities":{"hashtags":[],"symbols":[],"user_mentions":[],"urls":[{"url":"http://t.co/RcVJVy1JK0","expanded_url":"http://womanwithcatinbag.paulmckellar.com/","display_url":"womanwithcatinbag.paulmckellar.com","indices":["34","56"]}]},"display_text_range":["0","56"],"favorite_count":"1","id_str":"617791866067521536","truncated":false,"retweet_count":"0","id":"617791866067521536","possibly_sensitive":false,"created_at":"Sun Jul 05 20:27:13 +0000 2015","favorited":false,"full_text":"I call it \"woman with cat in bag\" http://t.co/RcVJVy1JK0","lang":"en"}