[{"retweeted":false,"source":"<a href=\"http://twitter.com\" rel=\"nofollow\">Twitter Web Client</a>","entities":{"hashtags":[],"symbols":[],"user_mentions":[],"urls":[]},"display_text_range":["0","98"],"favorite_count":"24","id_str":"436546352143532034","truncated":false,"retweet_count":"16","id":"436546352143532034","created_at":"Thu Feb 20 17:02:15 +0000 2014","favorited":false,"full_text":"Can someone write an article explaining why facebook bought whatsapp? I feel like there is a void.","lang":"en"},{"coordinates":{"type":"Point","coordinates":["-122.42175972","37.76434862"]},"retweeted":false,"source":"<a href=\"http://twitter.com/download/iphone\" rel=\"nofollow\">Twitter for iPhone</a>","entities":{"hashtags":[],"symbols":[],"user_mentions":[],"urls":[]},"display_text_range":["0","59"],"favorite_count":"15","geo":{"type":"Point","coordinates":["37.76434862","-122.42175972"]},"id_str":"435668101456089088","truncated":false,"retweet_count":"4","id":"435668101456089088","created_at":"Tue Feb 18 06:52:24 +0000 2014","favorited":false,"full_text":"There are more ways to live your life than you can imagine.","lang":"en"},{"retweeted":false,"source":"<a href=\"http://www.apple.com\" rel=\"nofollow\">iOS</a>","entities":{"user_mentions":[],"urls":[],"symbols":[],"media":[{"expanded_url":"https://twitter.com/pm/status/436318353573949440/photo/1","indices":["20","42"],"url":"http://t.co/dE1kf58vSd","media_url":"http://pbs.twimg.com/media/Bg4dOxCCUAAmDnh.jpg","id_str":"436318353418768384","id":"436318353418768384","media_url_https":"https://pbs.twimg.com/media/Bg4dOxCCUAAmDnh.jpg","sizes":{"thumb":{"w":"150","h":"150","resize":"crop"},"medium":{"w":"612","h":"816","resize":"fit"},"small":{"w":"510","h":"680","resize":"fit"},"large":{"w":"612","h":"816","resize":"fit"}},"type":"photo","display_url":"pic.twitter.com/dE1kf58vSd"}],"hashtags":[]},"display_text_range":["0","42"],"favorite_count":"13","id_str":"436318353573949440","truncated":false,"retweet_count":"2","id":"436318353573949440","possibly_sensitive":false,"created_at":"Thu Feb 20 01:56:16 +0000 2014","favorited":false,"full_text":"Makerbot thug life. http://t.co/dE1kf58vSd","lang":"en","extended_entities":{"media":[{"expanded_url":"https://twitter.com/pm/status/436318353573949440/photo/1","indices":["20","42"],"url":"http://t.co/dE1kf58vSd","media_url":"http://pbs.twimg.com/media/Bg4dOxCCUAAmDnh.jpg","id_str":"436318353418768384","id":"436318353418768384","media_url_https":"https://pbs.twimg.com/media/Bg4dOxCCUAAmDnh.jpg","sizes":{"thumb":{"w":"150","h":"150","resize":"crop"},"medium":{"w":"612","h":"816","resize":"fit"},"small":{"w":"510","h":"680","resize":"fit"},"large":{"w":"612","h":"816","resize":"fit"}},"type":"photo","display_url":"pic.twitter.com/dE1kf58vSd"}]}},{"retweeted":false,"source":"<a href=\"http://twitter.com\" rel=\"nofollow\">Twitter Web Client</a>","entities":{"hashtags":[],"symbols":[],"user_mentions":[],"urls":[]},"display_text_range":["0","74"],"favorite_count":"11","id_str":"436747266435465216","truncated":false,"retweet_count":"1","id":"436747266435465216","created_at":"Fri Feb 21 06:20:37 +0000 2014","favorited":false,"full_text":"A bunch of old friends had a good day today. You know who you are. Cheers.","lang":"en"},{"coordinates":{"type":"Point","coordinates":["-122.39273032","37.77888648"]},"retweeted":false,"source":"<a href=\"http://twitter.com/download/iphone\" rel=\"nofollow\">Twitter for iPhone</a>","entities":{"hashtags":[],"symbols":[],"user_mentions":[],"urls":[]},"display_text_range":["0","127"],"favorite_count":"11","geo":{"type":"Point","coordinates":["37.77888648","-122.39273032"]},"id_str":"433718836160786432","truncated":false,"retweet_count":"2","id":"433718836160786432","created_at":"Wed Feb 12 21:46:43 +0000 2014","favorited":false,"full_text":"The flappy bird guy called out the clones that he liked a lot. Very counter culture to the mentality of \"I'm a genius inventor\"","lang":"en"},{"retweeted":false,"source":"<a href=\"http://twitter.com\" rel=\"nofollow\">Twitter Web Client</a>","entities":{"hashtags":[],"symbols":[],"user_mentions":[],"urls":[]},"display_text_range":["0","57"],"favorite_count":"11","id_str":"437761247568617472","truncated":false,"retweet_count":"2","id":"437761247568617472","created_at":"Mon Feb 24 01:29:49 +0000 2014","favorited":false,"full_text":"Those that don't know Rails and doomed to reinvent Rails.","lang":"en"},{"coordinates":{"type":"Point","coordinates":["-122.4214028","37.759855"]},"retweeted":false,"source":"<a href=\"http://twitter.com/download/iphone\" rel=\"nofollow\">Twitter for iPhone</a>","entities":{"user_mentions":[{"name":"Square","screen_name":"Square","indices":["48","55"],"id_str":"93017945","id":"93017945"},{"name":"Robert Andersen","screen_name":"rsa","indices":["66","70"],"id_str":"6735","id":"6735"},{"name":"jack 🌍🌏🌎","screen_name":"jack","indices":["71","76"],"id_str":"12","id":"12"}],"urls":[],"symbols":[],"media":[{"expanded_url":"https://twitter.com/pm/status/437349860384051200/photo/1","indices":["77","99"],"url":"http://t.co/pZ1ROMUZPp","media_url":"http://pbs.twimg.com/media/BhHHYXVCMAA9ETV.jpg","id_str":"437349860224675840","id":"437349860224675840","media_url_https":"https://pbs.twimg.com/media/BhHHYXVCMAA9ETV.jpg","sizes":{"small":{"w":"680","h":"680","resize":"fit"},"thumb":{"w":"150","h":"150","resize":"crop"},"medium":{"w":"1024","h":"1024","resize":"fit"},"large":{"w":"1024","h":"1024","resize":"fit"}},"type":"photo","display_url":"pic.twitter.com/pZ1ROMUZPp"}],"hashtags":[]},"display_text_range":["0","99"],"favorite_count":"9","geo":{"type":"Point","coordinates":["37.759855","-122.4214028"]},"id_str":"437349860384051200","truncated":false,"retweet_count":"2","id":"437349860384051200","possibly_sensitive":false,"created_at":"Sat Feb 22 22:15:06 +0000 2014","favorited":false,"full_text":"Amos Goldblum did a good job of simplifying the @square logo. /cc @rsa @jack http://t.co/pZ1ROMUZPp","lang":"en","extended_entities":{"media":[{"expanded_url":"https://twitter.com/pm/status/437349860384051200/photo/1","indices":["77","99"],"url":"http://t.co/pZ1ROMUZPp","media_url":"http://pbs.twimg.com/media/BhHHYXVCMAA9ETV.jpg","id_str":"437349860224675840","id":"437349860224675840","media_url_https":"https://pbs.twimg.com/media/BhHHYXVCMAA9ETV.jpg","sizes":{"small":{"w":"680","h":"680","resize":"fit"},"thumb":{"w":"150","h":"150","resize":"crop"},"medium":{"w":"1024","h":"1024","resize":"fit"},"large":{"w":"1024","h":"1024","resize":"fit"}},"type":"photo","display_url":"pic.twitter.com/pZ1ROMUZPp"}]}},{"retweeted":false,"source":"<a href=\"http://twitter.com\" rel=\"nofollow\">Twitter Web Client</a>","entities":{"hashtags":[],"symbols":[],"user_mentions":[{"name":"Paul Graham","screen_name":"paulg","indices":["43","49"],"id_str":"183749519","id":"183749519"},{"name":"Y Combinator","screen_name":"ycombinator","indices":["61","73"],"id_str":"113130846","id":"113130846"}],"urls":[]},"display_text_range":["0","101"],"favorite_count":"9","id_str":"438373101139537920","truncated":false,"retweet_count":"0","id":"438373101139537920","created_at":"Tue Feb 25 18:01:06 +0000 2014","favorited":false,"full_text":"I'm really appreciative of the opportunity @paulg and all of @ycombinator gave me almost 8 years ago.","lang":"en"},{"retweeted":false,"source":"<a href=\"http://twitter.com\" rel=\"nofollow\">Twitter Web Client</a>","entities":{"hashtags":[],"symbols":[],"user_mentions":[],"urls":[]},"display_text_range":["0","97"],"favorite_count":"9","id_str":"430468524226539521","truncated":false,"retweet_count":"0","id":"430468524226539521","created_at":"Mon Feb 03 22:31:08 +0000 2014","favorited":false,"full_text":"Hoping 'Fiftythree Paper' responds by making a social network called Facebook. I would Like that.","lang":"en"},{"retweeted":false,"source":"<a href=\"http://twitter.com\" rel=\"nofollow\">Twitter Web Client</a>","entities":{"hashtags":[],"symbols":[],"user_mentions":[],"urls":[]},"display_text_range":["0","42"],"favorite_count":"8","id_str":"438066532774473729","truncated":false,"retweet_count":"2","id":"438066532774473729","created_at":"Mon Feb 24 21:42:54 +0000 2014","favorited":false,"full_text":"We're not mobile first, we're mobile only.","lang":"en"},{"coordinates":{"type":"Point","coordinates":["-122.41175707","37.76181162"]},"retweeted":false,"source":"<a href=\"http://twitter.com/download/iphone\" rel=\"nofollow\">Twitter for iPhone</a>","entities":{"hashtags":[],"symbols":[],"user_mentions":[],"urls":[]},"display_text_range":["0","69"],"favorite_count":"8","geo":{"type":"Point","coordinates":["37.76181162","-122.41175707"]},"id_str":"434365157389508608","truncated":false,"retweet_count":"0","id":"434365157389508608","created_at":"Fri Feb 14 16:34:58 +0000 2014","favorited":false,"full_text":"I used to tell people at parties I wrote short stories for computers.","lang":"en"},{"coordinates":{"type":"Point","coordinates":["-122.42176351","37.76187852"]},"retweeted":false,"source":"<a href=\"http://twitter.com/download/iphone\" rel=\"nofollow\">Twitter for iPhone</a>","entities":{"hashtags":[],"symbols":[],"user_mentions":[],"urls":[]},"display_text_range":["0","99"],"favorite_count":"7","geo":{"type":"Point","coordinates":["37.76187852","-122.42176351"]},"id_str":"435261593866100737","truncated":false,"retweet_count":"0","id":"435261593866100737","created_at":"Mon Feb 17 03:57:05 +0000 2014","favorited":false,"full_text":"Yelp reviews for band performances. So I know which shows might be good and which bands throw down.","lang":"en"},{"retweeted":false,"source":"<a href=\"http://twitter.com\" rel=\"nofollow\">Twitter Web Client</a>","entities":{"hashtags":[],"symbols":[],"user_mentions":[],"urls":[{"url":"http://t.co/eRljC6xjjQ","expanded_url":"http://mixioapp.com/","display_url":"mixioapp.com","indices":["63","85"]}]},"display_text_range":["0","85"],"favorite_count":"7","id_str":"438362878043631616","truncated":false,"retweet_count":"6","id":"438362878043631616","possibly_sensitive":false,"created_at":"Tue Feb 25 17:20:29 +0000 2014","favorited":false,"full_text":"Mixio is the best parody html5 working camera app of all time. http://t.co/eRljC6xjjQ","lang":"en"},{"retweeted":false,"source":"<a href=\"http://twitter.com\" rel=\"nofollow\">Twitter Web Client</a>","entities":{"hashtags":[],"symbols":[],"user_mentions":[],"urls":[]},"display_text_range":["0","87"],"favorite_count":"7","id_str":"437629839235756032","truncated":false,"retweet_count":"1","id":"437629839235756032","created_at":"Sun Feb 23 16:47:39 +0000 2014","favorited":false,"full_text":"I've spent more money at Blue Bottle than Uber. Surprised me too. Anyways, coffee time!","lang":"en"},{"retweeted":false,"source":"<a href=\"http://twitter.com\" rel=\"nofollow\">Twitter Web Client</a>","entities":{"hashtags":[],"symbols":[],"user_mentions":[],"urls":[{"url":"http://t.co/b1U8XLp3ca","expanded_url":"http://www.youtube.com/watch?v=1hlCEIUATzg","display_url":"youtube.com/watch?v=1hlCEI…","indices":["61","83"]}]},"display_text_range":["0","83"],"favorite_count":"7","id_str":"434564454643036160","truncated":false,"retweet_count":"4","id":"434564454643036160","possibly_sensitive":false,"created_at":"Sat Feb 15 05:46:54 +0000 2014","favorited":false,"full_text":"Ellen Page came out and her speech is awesome. Check it out: http://t.co/b1U8XLp3ca","lang":"en"},{"coordinates":{"type":"Point","coordinates":["-122.41252134","37.76475665"]},"retweeted":false,"source":"<a href=\"http://twitter.com/download/iphone\" rel=\"nofollow\">Twitter for iPhone</a>","entities":{"hashtags":[],"symbols":[],"user_mentions":[],"urls":[]},"display_text_range":["0","59"],"favorite_count":"6","geo":{"type":"Point","coordinates":["37.76475665","-122.41252134"]},"id_str":"430215296360513536","truncated":false,"retweet_count":"3","id":"430215296360513536","created_at":"Mon Feb 03 05:44:54 +0000 2014","favorited":false,"full_text":"\"In the future, people will do _____, obviously\" - startups","lang":"en"},{"retweeted":false,"source":"<a href=\"http://twitter.com\" rel=\"nofollow\">Twitter Web Client</a>","entities":{"hashtags":[],"symbols":[],"user_mentions":[],"urls":[]},"display_text_range":["0","69"],"favorite_count":"6","id_str":"435493183204515840","truncated":false,"retweet_count":"0","id":"435493183204515840","created_at":"Mon Feb 17 19:17:20 +0000 2014","favorited":false,"full_text":"Entrepreneur doesn't get snapchat. Suggests snapchat could be better.","lang":"en"},{"coordinates":{"type":"Point","coordinates":["-122.41241139","37.76465368"]},"retweeted":false,"source":"<a href=\"http://twitter.com/download/iphone\" rel=\"nofollow\">Twitter for iPhone</a>","entities":{"hashtags":[],"symbols":[],"user_mentions":[{"name":"NPR","screen_name":"NPR","indices":["1","5"],"id_str":"5392522","id":"5392522"}],"urls":[]},"display_text_range":["0","59"],"favorite_count":"6","geo":{"type":"Point","coordinates":["37.76465368","-122.41241139"]},"id_str":"438351218734141440","truncated":false,"retweet_count":"0","id":"438351218734141440","created_at":"Tue Feb 25 16:34:09 +0000 2014","favorited":false,"full_text":".@NPR please update your app or open source it. I can help.","lang":"en"},{"coordinates":{"type":"Point","coordinates":["-122.41958183","37.76279122"]},"retweeted":false,"source":"<a href=\"http://twitter.com/download/iphone\" rel=\"nofollow\">Twitter for iPhone</a>","entities":{"hashtags":[],"symbols":[],"user_mentions":[],"urls":[]},"display_text_range":["0","40"],"favorite_count":"5","geo":{"type":"Point","coordinates":["37.76279122","-122.41958183"]},"id_str":"437672563380994048","truncated":false,"retweet_count":"0","id":"437672563380994048","created_at":"Sun Feb 23 19:37:25 +0000 2014","favorited":false,"full_text":"And a faraday cage, for their cellphone.","lang":"en"},{"retweeted":false,"source":"<a href=\"http://twitter.com\" rel=\"nofollow\">Twitter Web Client</a>","entities":{"hashtags":[],"symbols":[],"user_mentions":[],"urls":[]},"display_text_range":["0","75"],"favorite_count":"5","id_str":"437683826328760321","truncated":false,"retweet_count":"2","id":"437683826328760321","created_at":"Sun Feb 23 20:22:10 +0000 2014","favorited":false,"full_text":"Cash is actually a tool that is perfect for criminals. We should outlaw it.","lang":"en"},{"coordinates":{"type":"Point","coordinates":["-122.42193978","37.76655588"]},"retweeted":false,"source":"<a href=\"http://twitter.com/download/iphone\" rel=\"nofollow\">Twitter for iPhone</a>","entities":{"hashtags":[],"symbols":[],"user_mentions":[],"urls":[]},"display_text_range":["0","98"],"favorite_count":"5","geo":{"type":"Point","coordinates":["37.76655588","-122.42193978"]},"id_str":"435878840699609088","truncated":false,"retweet_count":"0","id":"435878840699609088","created_at":"Tue Feb 18 20:49:48 +0000 2014","favorited":false,"full_text":"Google is opening an office across the street from my house. My coffee shop is going to be fucked.","lang":"en"},{"retweeted":false,"source":"<a href=\"http://twitter.com\" rel=\"nofollow\">Twitter Web Client</a>","entities":{"hashtags":[],"symbols":[],"user_mentions":[],"urls":[{"url":"http://t.co/nAMZoqt4Pe","expanded_url":"http://bit.ly/1mlN0yR","display_url":"bit.ly/1mlN0yR","indices":["75","97"]}]},"display_text_range":["0","125"],"favorite_count":"5","id_str":"437316051764654080","truncated":false,"retweet_count":"4","id":"437316051764654080","possibly_sensitive":false,"created_at":"Sat Feb 22 20:00:46 +0000 2014","favorited":false,"full_text":"I'm using Threema because I want to support privacy on the internet (1.99) http://t.co/nAMZoqt4Pe What do you think about it?","lang":"en"},{"retweeted":false,"source":"<a href=\"http://twitter.com\" rel=\"nofollow\">Twitter Web Client</a>","entities":{"hashtags":[],"symbols":[],"user_mentions":[],"urls":[]},"display_text_range":["0","63"],"favorite_count":"4","id_str":"436271721608265729","truncated":false,"retweet_count":"0","id":"436271721608265729","created_at":"Wed Feb 19 22:50:58 +0000 2014","favorited":false,"full_text":"I wonder how many people in the valley just installed whatsapp.","lang":"en"},{"retweeted":false,"source":"<a href=\"http://twitter.com\" rel=\"nofollow\">Twitter Web Client</a>","entities":{"hashtags":[],"symbols":[],"user_mentions":[],"urls":[]},"display_text_range":["0","41"],"favorite_count":"4","id_str":"431854116671729664","truncated":false,"retweet_count":"0","id":"431854116671729664","created_at":"Fri Feb 07 18:16:59 +0000 2014","favorited":false,"full_text":"Yelp reviews for Github repositories. Plz","lang":"en"},{"coordinates":{"type":"Point","coordinates":["-122.41736356","37.76191195"]},"retweeted":false,"source":"<a href=\"http://twitter.com/download/iphone\" rel=\"nofollow\">Twitter for iPhone</a>","entities":{"user_mentions":[{"name":"beamer","screen_name":"beamercola","indices":["18","29"],"id_str":"693823","id":"693823"}],"urls":[],"symbols":[],"media":[{"expanded_url":"https://twitter.com/pm/status/438396814077616128/photo/1","indices":["30","52"],"url":"http://t.co/kN4qQ13Zsb","media_url":"http://pbs.twimg.com/media/BhV_lFuCYAAEcOM.jpg","id_str":"438396813905649664","id":"438396813905649664","media_url_https":"https://pbs.twimg.com/media/BhV_lFuCYAAEcOM.jpg","sizes":{"thumb":{"w":"150","h":"150","resize":"crop"},"small":{"w":"510","h":"680","resize":"fit"},"large":{"w":"768","h":"1024","resize":"fit"},"medium":{"w":"768","h":"1024","resize":"fit"}},"type":"photo","display_url":"pic.twitter.com/kN4qQ13Zsb"}],"hashtags":[]},"display_text_range":["0","52"],"favorite_count":"4","geo":{"type":"Point","coordinates":["37.76191195","-122.41736356"]},"id_str":"438396814077616128","truncated":false,"retweet_count":"1","id":"438396814077616128","possibly_sensitive":false,"created_at":"Tue Feb 25 19:35:20 +0000 2014","favorited":false,"full_text":"What is this? /cc @beamercola http://t.co/kN4qQ13Zsb","lang":"en","extended_entities":{"media":[{"expanded_url":"https://twitter.com/pm/status/438396814077616128/photo/1","indices":["30","52"],"url":"http://t.co/kN4qQ13Zsb","media_url":"http://pbs.twimg.com/media/BhV_lFuCYAAEcOM.jpg","id_str":"438396813905649664","id":"438396813905649664","media_url_https":"https://pbs.twimg.com/media/BhV_lFuCYAAEcOM.jpg","sizes":{"thumb":{"w":"150","h":"150","resize":"crop"},"small":{"w":"510","h":"680","resize":"fit"},"large":{"w":"768","h":"1024","resize":"fit"},"medium":{"w":"768","h":"1024","resize":"fit"}},"type":"photo","display_url":"pic.twitter.com/kN4qQ13Zsb"}]}},{"retweeted":false,"source":"<a href=\"http://twitter.com\" rel=\"nofollow\">Twitter Web Client</a>","entities":{"hashtags":[],"symbols":[],"user_mentions":[{"name":"The New York Times","screen_name":"nytimes","indices":["23","31"],"id_str":"807095","id":"807095"}],"urls":[{"url":"http://t.co/6qFpszXCGj","expanded_url":"http://nyti.ms/1bwPPXl","display_url":"nyti.ms/1bwPPXl","indices":["32","54"]}]},"display_text_range":["0","54"],"favorite_count":"4","id_str":"431854739509100544","truncated":false,"retweet_count":"2","id":"431854739509100544","possibly_sensitive":false,"created_at":"Fri Feb 07 18:19:28 +0000 2014","favorited":false,"full_text":"Thanks Nick, WUT WUT @ @nytimes http://t.co/6qFpszXCGj","lang":"en"},{"retweeted":false,"source":"<a href=\"http://twitter.com\" rel=\"nofollow\">Twitter Web Client</a>","entities":{"hashtags":[{"text":"NetNeutrality","indices":["17","31"]}],"symbols":[],"user_mentions":[],"urls":[]},"display_text_range":["0","31"],"favorite_count":"4","id_str":"432209696078823425","truncated":false,"retweet_count":"2","id":"432209696078823425","created_at":"Sat Feb 08 17:49:56 +0000 2014","favorited":false,"full_text":"Winter is coming #NetNeutrality","lang":"en"},{"retweeted":false,"source":"<a href=\"http://twitter.com\" rel=\"nofollow\">Twitter Web Client</a>","entities":{"hashtags":[],"symbols":[],"user_mentions":[{"name":"Paul Graham","screen_name":"paulg","indices":["0","6"],"id_str":"183749519","id":"183749519"},{"name":"Bill Gates","screen_name":"BillGates","indices":["7","17"],"id_str":"50393960","id":"50393960"}],"urls":[]},"display_text_range":["0","129"],"favorite_count":"4","in_reply_to_status_id_str":"429664371195658240","id_str":"429681245878886400","in_reply_to_user_id":"183749519","truncated":false,"retweet_count":"0","id":"429681245878886400","in_reply_to_status_id":"429664371195658240","created_at":"Sat Feb 01 18:22:46 +0000 2014","favorited":false,"full_text":"@paulg @BillGates \"It’s 140 characters. It’s so few characters. If you need a ghostwriter for that, I feel sorry for you.\" - Shaq","lang":"en","in_reply_to_screen_name":"paulg","in_reply_to_user_id_str":"183749519"},{"coordinates":{"type":"Point","coordinates":["-122.41167531","37.76177557"]},"retweeted":false,"source":"<a href=\"http://twitter.com/download/iphone\" rel=\"nofollow\">Twitter for iPhone</a>","entities":{"hashtags":[],"symbols":[],"user_mentions":[{"name":"Bored Elon Musk","screen_name":"BoredElonMusk","indices":["66","80"],"id_str":"1666038950","id":"1666038950"}],"urls":[]},"display_text_range":["0","133"],"favorite_count":"4","geo":{"type":"Point","coordinates":["37.76177557","-122.41167531"]},"id_str":"437985785187270656","truncated":false,"retweet_count":"0","id":"437985785187270656","created_at":"Mon Feb 24 16:22:03 +0000 2014","favorited":false,"full_text":"Prediction: Eventually, through repetition and audience building, @BoredElonMusk has an idea which gets kickstarted and becomes real.","lang":"en"},{"retweeted":false,"source":"<a href=\"http://twitter.com\" rel=\"nofollow\">Twitter Web Client</a>","entities":{"hashtags":[],"symbols":[],"user_mentions":[],"urls":[]},"display_text_range":["0","64"],"favorite_count":"3","id_str":"438855372749565952","truncated":false,"retweet_count":"0","id":"438855372749565952","created_at":"Thu Feb 27 01:57:29 +0000 2014","favorited":false,"full_text":"Yesterday I bought a text editor, today I switched text editors.","lang":"en"},{"coordinates":{"type":"Point","coordinates":["-122.15817807","37.44256612"]},"retweeted":false,"source":"<a href=\"http://twitter.com/download/iphone\" rel=\"nofollow\">Twitter for iPhone</a>","entities":{"hashtags":[],"symbols":[],"user_mentions":[],"urls":[]},"display_text_range":["0","70"],"favorite_count":"3","geo":{"type":"Point","coordinates":["37.44256612","-122.15817807"]},"id_str":"439139322491449344","truncated":false,"retweet_count":"0","id":"439139322491449344","created_at":"Thu Feb 27 20:45:47 +0000 2014","favorited":false,"full_text":"I'm frustrated by activists that try and change humans with pamphlets.","lang":"en"},{"retweeted":false,"source":"<a href=\"http://twitter.com\" rel=\"nofollow\">Twitter Web Client</a>","entities":{"hashtags":[],"symbols":[],"user_mentions":[],"urls":[{"url":"http://t.co/uNTaT3FscT","expanded_url":"http://en.wikipedia.org/wiki/Alice_and_Bob","display_url":"en.wikipedia.org/wiki/Alice_and…","indices":["98","120"]}]},"display_text_range":["0","120"],"favorite_count":"3","id_str":"432719814759432192","truncated":false,"retweet_count":"0","id":"432719814759432192","possibly_sensitive":false,"created_at":"Mon Feb 10 03:36:58 +0000 2014","favorited":false,"full_text":"I'm going to have three kids and name them Alice, Bob, and Eve, just in case someone is watching. http://t.co/uNTaT3FscT","lang":"en"},{"coordinates":{"type":"Point","coordinates":["-122.42208174","37.76706578"]},"retweeted":false,"source":"<a href=\"http://twitter.com/download/iphone\" rel=\"nofollow\">Twitter for iPhone</a>","entities":{"hashtags":[],"symbols":[],"user_mentions":[],"urls":[]},"display_text_range":["0","65"],"favorite_count":"3","geo":{"type":"Point","coordinates":["37.76706578","-122.42208174"]},"id_str":"435881293713117184","truncated":false,"retweet_count":"0","id":"435881293713117184","created_at":"Tue Feb 18 20:59:33 +0000 2014","favorited":false,"full_text":"If google fiber built an apartment complex in SF, I'd move there.","lang":"en"},{"retweeted":false,"source":"<a href=\"http://twitter.com\" rel=\"nofollow\">Twitter Web Client</a>","entities":{"hashtags":[],"symbols":[],"user_mentions":[],"urls":[]},"display_text_range":["0","104"],"favorite_count":"3","id_str":"435611319568322560","truncated":false,"retweet_count":"1","id":"435611319568322560","created_at":"Tue Feb 18 03:06:46 +0000 2014","favorited":false,"full_text":"\"From now on I'm going to misattribute everything I quote because: fun.\" - james bond, or justin beiber.","lang":"en"},{"retweeted":false,"source":"<a href=\"http://twitter.com\" rel=\"nofollow\">Twitter Web Client</a>","entities":{"hashtags":[],"symbols":[],"user_mentions":[],"urls":[]},"display_text_range":["0","99"],"favorite_count":"3","id_str":"430470015796535296","truncated":false,"retweet_count":"0","id":"430470015796535296","created_at":"Mon Feb 03 22:37:04 +0000 2014","favorited":false,"full_text":"The new tweet button on the web is HUGE. As if the size was keeping me from tweeting with you guys.","lang":"en"},{"retweeted":false,"source":"<a href=\"http://twitter.com\" rel=\"nofollow\">Twitter Web Client</a>","entities":{"hashtags":[],"symbols":[],"user_mentions":[],"urls":[{"url":"http://t.co/oTcLGyjWDS","expanded_url":"http://bit.ly/1fRP7Yy","display_url":"bit.ly/1fRP7Yy","indices":["93","115"]}]},"display_text_range":["0","115"],"favorite_count":"3","id_str":"431147388506365952","truncated":false,"retweet_count":"1","id":"431147388506365952","possibly_sensitive":false,"created_at":"Wed Feb 05 19:28:42 +0000 2014","favorited":false,"full_text":"Can we block anyone who votes against network neutrality from accessing any of our websites? http://t.co/oTcLGyjWDS","lang":"en"},{"coordinates":{"type":"Point","coordinates":["-122.41241571","37.76467364"]},"retweeted":false,"source":"<a href=\"http://twitter.com/download/iphone\" rel=\"nofollow\">Twitter for iPhone</a>","entities":{"hashtags":[],"symbols":[],"user_mentions":[],"urls":[]},"display_text_range":["0","91"],"favorite_count":"3","geo":{"type":"Point","coordinates":["37.76467364","-122.41241571"]},"id_str":"437416234909315072","truncated":false,"retweet_count":"0","id":"437416234909315072","created_at":"Sun Feb 23 02:38:51 +0000 2014","favorited":false,"full_text":"Kind of want to change my byline to 'former kid' because, you know, everyone could be that.","lang":"en"},{"coordinates":{"type":"Point","coordinates":["-122.32439849","37.56278392"]},"retweeted":false,"source":"<a href=\"http://twitter.com/download/iphone\" rel=\"nofollow\">Twitter for iPhone</a>","entities":{"user_mentions":[],"urls":[],"symbols":[],"media":[{"expanded_url":"https://twitter.com/pm/status/436613296134029312/photo/1","indices":["74","96"],"url":"http://t.co/swYzA1gLno","media_url":"http://pbs.twimg.com/media/Bg8per0IgAA8w8f.jpg","id_str":"436613296012427264","id":"436613296012427264","media_url_https":"https://pbs.twimg.com/media/Bg8per0IgAA8w8f.jpg","sizes":{"thumb":{"w":"150","h":"150","resize":"crop"},"small":{"w":"383","h":"680","resize":"fit"},"medium":{"w":"576","h":"1024","resize":"fit"},"large":{"w":"576","h":"1024","resize":"fit"}},"type":"photo","display_url":"pic.twitter.com/swYzA1gLno"}],"hashtags":[]},"display_text_range":["0","96"],"favorite_count":"3","geo":{"type":"Point","coordinates":["37.56278392","-122.32439849"]},"id_str":"436613296134029312","truncated":false,"retweet_count":"2","id":"436613296134029312","possibly_sensitive":false,"created_at":"Thu Feb 20 21:28:16 +0000 2014","favorited":false,"full_text":"Next time you make a joke about stickers, remember this App Store review. http://t.co/swYzA1gLno","lang":"en","extended_entities":{"media":[{"expanded_url":"https://twitter.com/pm/status/436613296134029312/photo/1","indices":["74","96"],"url":"http://t.co/swYzA1gLno","media_url":"http://pbs.twimg.com/media/Bg8per0IgAA8w8f.jpg","id_str":"436613296012427264","id":"436613296012427264","media_url_https":"https://pbs.twimg.com/media/Bg8per0IgAA8w8f.jpg","sizes":{"thumb":{"w":"150","h":"150","resize":"crop"},"small":{"w":"383","h":"680","resize":"fit"},"medium":{"w":"576","h":"1024","resize":"fit"},"large":{"w":"576","h":"1024","resize":"fit"}},"type":"photo","display_url":"pic.twitter.com/swYzA1gLno"}]}},{"coordinates":{"type":"Point","coordinates":["-122.42175274","37.76438953"]},"retweeted":false,"source":"<a href=\"http://twitter.com/download/iphone\" rel=\"nofollow\">Twitter for iPhone</a>","entities":{"hashtags":[],"symbols":[],"user_mentions":[],"urls":[]},"display_text_range":["0","55"],"favorite_count":"3","geo":{"type":"Point","coordinates":["37.76438953","-122.42175274"]},"id_str":"434535659273867264","truncated":false,"retweet_count":"3","id":"434535659273867264","created_at":"Sat Feb 15 03:52:29 +0000 2014","favorited":false,"full_text":"Wait. Facebook is worth more than amazon? (171&gt;164B)","lang":"en"},{"retweeted":false,"source":"<a href=\"http://twitter.com\" rel=\"nofollow\">Twitter Web Client</a>","entities":{"hashtags":[],"symbols":[],"user_mentions":[],"urls":[]},"display_text_range":["0","50"],"favorite_count":"3","id_str":"432269885289148416","truncated":false,"retweet_count":"2","id":"432269885289148416","created_at":"Sat Feb 08 21:49:06 +0000 2014","favorited":false,"full_text":"THE PONZI SCHEME WORKED FOR ME. I MADE 1.50 CENTS.","lang":"en"},{"retweeted":false,"source":"<a href=\"http://twitter.com\" rel=\"nofollow\">Twitter Web Client</a>","entities":{"hashtags":[],"symbols":[],"user_mentions":[],"urls":[]},"display_text_range":["0","55"],"favorite_count":"3","id_str":"436545509876961280","truncated":false,"retweet_count":"1","id":"436545509876961280","created_at":"Thu Feb 20 16:58:54 +0000 2014","favorited":false,"full_text":"Can we bring back the -ster suffix. Twitster, Facester?","lang":"en"},{"retweeted":false,"source":"<a href=\"http://twitter.com\" rel=\"nofollow\">Twitter Web Client</a>","entities":{"hashtags":[],"symbols":[],"user_mentions":[],"urls":[]},"display_text_range":["0","108"],"favorite_count":"3","id_str":"434440997104140288","truncated":false,"retweet_count":"1","id":"434440997104140288","created_at":"Fri Feb 14 21:36:19 +0000 2014","favorited":false,"full_text":"I will send you free money! Reply to me if you want to try out cryptocurrency, for the first time, for free.","lang":"en"},{"coordinates":{"type":"Point","coordinates":["-122.4196233","37.76269995"]},"retweeted":false,"source":"<a href=\"http://twitter.com/download/iphone\" rel=\"nofollow\">Twitter for iPhone</a>","entities":{"hashtags":[],"symbols":[],"user_mentions":[],"urls":[]},"display_text_range":["0","57"],"favorite_count":"3","geo":{"type":"Point","coordinates":["37.76269995","-122.4196233"]},"id_str":"437672462881271808","truncated":false,"retweet_count":"0","id":"437672462881271808","created_at":"Sun Feb 23 19:37:01 +0000 2014","favorited":false,"full_text":"Hanging out with someone who has 30k dollars of Dogecoin.","lang":"en"},{"retweeted":false,"source":"<a href=\"http://twitter.com\" rel=\"nofollow\">Twitter Web Client</a>","entities":{"hashtags":[],"symbols":[],"user_mentions":[],"urls":[]},"display_text_range":["0","79"],"favorite_count":"3","id_str":"431124650190319617","truncated":false,"retweet_count":"0","id":"431124650190319617","created_at":"Wed Feb 05 17:58:21 +0000 2014","favorited":false,"full_text":"Replying to customer support emails this morning. A forgotten pleasure of mine.","lang":"en"},{"retweeted":false,"source":"<a href=\"http://twitter.com\" rel=\"nofollow\">Twitter Web Client</a>","entities":{"hashtags":[],"symbols":[],"user_mentions":[],"urls":[{"url":"https://t.co/sbx1hjWxzn","expanded_url":"https://www.kickstarter.com/projects/hellobragi/the-dash-wireless-smart-in-ear-headphones","display_url":"kickstarter.com/projects/hello…","indices":["83","106"]}]},"display_text_range":["0","106"],"favorite_count":"2","id_str":"433302173716205568","truncated":false,"retweet_count":"0","id":"433302173716205568","possibly_sensitive":false,"created_at":"Tue Feb 11 18:11:03 +0000 2014","favorited":false,"full_text":"So many cool things are being made right now. Today I'm geeking out about the Dash https://t.co/sbx1hjWxzn","lang":"en"},{"retweeted":false,"source":"<a href=\"http://twitter.com\" rel=\"nofollow\">Twitter Web Client</a>","entities":{"hashtags":[],"symbols":[],"user_mentions":[],"urls":[]},"display_text_range":["0","63"],"favorite_count":"2","id_str":"433988477542100993","truncated":false,"retweet_count":"0","id":"433988477542100993","created_at":"Thu Feb 13 15:38:10 +0000 2014","favorited":false,"full_text":"My electricity and water always work, my internet barely works.","lang":"en"},{"retweeted":false,"source":"<a href=\"http://twitter.com\" rel=\"nofollow\">Twitter Web Client</a>","entities":{"hashtags":[],"symbols":[],"user_mentions":[{"name":"Justin 🌙🚀 Herrick","screen_name":"JAH2488","indices":["0","8"],"id_str":"17934912","id":"17934912"},{"name":"Gary Bernhardt","screen_name":"garybernhardt","indices":["9","23"],"id_str":"809685","id":"809685"},{"name":"steveklabnik","screen_name":"steveklabnik","indices":["24","37"],"id_str":"22386062","id":"22386062"}],"urls":[]},"display_text_range":["0","100"],"favorite_count":"2","in_reply_to_status_id_str":"431523314708672514","id_str":"431524202223374336","in_reply_to_user_id":"17934912","truncated":false,"retweet_count":"0","id":"431524202223374336","in_reply_to_status_id":"431523314708672514","created_at":"Thu Feb 06 20:26:01 +0000 2014","favorited":false,"full_text":"@JAH2488 @garybernhardt @steveklabnik they just have to allow me to use MY phone to manage MY money.","lang":"en","in_reply_to_screen_name":"JAH2488","in_reply_to_user_id_str":"17934912"},{"coordinates":{"type":"Point","coordinates":["-122.41837139","37.75367534"]},"retweeted":false,"source":"<a href=\"http://twitter.com/download/iphone\" rel=\"nofollow\">Twitter for iPhone</a>","entities":{"hashtags":[],"symbols":[],"user_mentions":[],"urls":[]},"display_text_range":["0","68"],"favorite_count":"2","geo":{"type":"Point","coordinates":["37.75367534","-122.41837139"]},"id_str":"431230784054120448","truncated":false,"retweet_count":"0","id":"431230784054120448","created_at":"Thu Feb 06 01:00:05 +0000 2014","favorited":false,"full_text":"I've been at the bank 10 minutes and hate my life. Please send help.","lang":"en"},{"retweeted":false,"source":"<a href=\"http://twitter.com\" rel=\"nofollow\">Twitter Web Client</a>","entities":{"hashtags":[],"symbols":[],"user_mentions":[],"urls":[]},"display_text_range":["0","138"],"favorite_count":"2","id_str":"437316921310969856","truncated":false,"retweet_count":"0","id":"437316921310969856","created_at":"Sat Feb 22 20:04:13 +0000 2014","favorited":false,"full_text":"I use \"favorite\" on twitter as \"read receipt\", and started unfaving things occasionally when it was just a \"read receipt\" not a \"favorite\"","lang":"en"},{"retweeted":false,"source":"<a href=\"http://twitter.com/download/iphone\" rel=\"nofollow\">Twitter for iPhone</a>","entities":{"hashtags":[],"symbols":[],"user_mentions":[{"name":"Buzz Andersen","screen_name":"buzz","indices":["0","5"],"id_str":"528","id":"528"},{"name":"meowrey","screen_name":"meowrey","indices":["6","14"],"id_str":"5984072","id":"5984072"},{"name":"Not Robert Andersen","screen_name":"powerclown","indices":["15","26"],"id_str":"107595104","id":"107595104"},{"name":"Robert Andersen","screen_name":"rsa","indices":["27","31"],"id_str":"6735","id":"6735"}],"urls":[]},"display_text_range":["0","67"],"favorite_count":"2","in_reply_to_status_id_str":"434043306759442432","id_str":"434046863214272512","in_reply_to_user_id":"528","truncated":false,"retweet_count":"1","id":"434046863214272512","in_reply_to_status_id":"434043306759442432","created_at":"Thu Feb 13 19:30:11 +0000 2014","favorited":false,"full_text":"@buzz @meowrey @powerclown @rsa I support powerclown hashtag on wut","lang":"en","in_reply_to_screen_name":"buzz","in_reply_to_user_id_str":"528"},{"coordinates":{"type":"Point","coordinates":["-122.41237484","37.76459131"]},"retweeted":false,"source":"<a href=\"http://twitter.com/download/iphone\" rel=\"nofollow\">Twitter for iPhone</a>","entities":{"hashtags":[],"symbols":[],"user_mentions":[],"urls":[]},"display_text_range":["0","106"],"favorite_count":"2","geo":{"type":"Point","coordinates":["37.76459131","-122.41237484"]},"id_str":"436374564486914048","truncated":false,"retweet_count":"1","id":"436374564486914048","created_at":"Thu Feb 20 05:39:38 +0000 2014","favorited":false,"full_text":"Apparently fan fiction started when Arthur Conan Doyle originally killed Sherlock and fans didn't like it.","lang":"en"},{"retweeted":false,"source":"<a href=\"http://twitter.com\" rel=\"nofollow\">Twitter Web Client</a>","entities":{"hashtags":[{"text":"unpopularopinion","indices":["100","117"]}],"symbols":[],"user_mentions":[],"urls":[]},"display_text_range":["0","117"],"favorite_count":"2","id_str":"431465121219485696","truncated":false,"retweet_count":"0","id":"431465121219485696","created_at":"Thu Feb 06 16:31:15 +0000 2014","favorited":false,"full_text":"I love facebook. My parents friends from college 30+ years ago are posting pictures of them. Great! #unpopularopinion","lang":"en"},{"coordinates":{"type":"Point","coordinates":["-122.41167091","37.76172358"]},"retweeted":false,"source":"<a href=\"http://twitter.com/download/iphone\" rel=\"nofollow\">Twitter for iPhone</a>","entities":{"hashtags":[],"symbols":[],"user_mentions":[],"urls":[]},"display_text_range":["0","75"],"favorite_count":"2","geo":{"type":"Point","coordinates":["37.76172358","-122.41167091"]},"id_str":"434364068317499393","truncated":false,"retweet_count":"1","id":"434364068317499393","created_at":"Fri Feb 14 16:30:38 +0000 2014","favorited":false,"full_text":"Calling yourself an artist sounds immodest. I want people to get over that.","lang":"en"},{"coordinates":{"type":"Point","coordinates":["-122.41248241","37.76458478"]},"retweeted":false,"source":"<a href=\"http://twitter.com/download/iphone\" rel=\"nofollow\">Twitter for iPhone</a>","entities":{"hashtags":[],"symbols":[],"user_mentions":[],"urls":[]},"display_text_range":["0","62"],"favorite_count":"2","geo":{"type":"Point","coordinates":["37.76458478","-122.41248241"]},"id_str":"436902094205755393","truncated":false,"retweet_count":"1","id":"436902094205755393","created_at":"Fri Feb 21 16:35:51 +0000 2014","favorited":false,"full_text":"Everything that happened yesterday, seems obvious to me today.","lang":"en"},{"coordinates":{"type":"Point","coordinates":["-122.41235361","37.76457727"]},"retweeted":false,"source":"<a href=\"http://twitter.com/download/iphone\" rel=\"nofollow\">Twitter for iPhone</a>","entities":{"hashtags":[],"symbols":[],"user_mentions":[],"urls":[]},"display_text_range":["0","114"],"favorite_count":"2","geo":{"type":"Point","coordinates":["37.76457727","-122.41235361"]},"id_str":"439106913117024256","truncated":false,"retweet_count":"0","id":"439106913117024256","created_at":"Thu Feb 27 18:37:00 +0000 2014","favorited":false,"full_text":"There were no bubbles before the news media existed. The tulip bubble was in the first media capital of the world.","lang":"en"},{"coordinates":{"type":"Point","coordinates":["-122.42195098","37.76463846"]},"retweeted":false,"source":"<a href=\"http://twitter.com/download/iphone\" rel=\"nofollow\">Twitter for iPhone</a>","entities":{"hashtags":[],"symbols":[],"user_mentions":[],"urls":[]},"display_text_range":["0","53"],"favorite_count":"2","geo":{"type":"Point","coordinates":["37.76463846","-122.42195098"]},"id_str":"437327137108787200","truncated":false,"retweet_count":"4","id":"437327137108787200","created_at":"Sat Feb 22 20:44:49 +0000 2014","favorited":false,"full_text":"\"We live in an era where privacy is a feature\" - Atif","lang":"en"},{"retweeted":false,"source":"<a href=\"http://twitter.com\" rel=\"nofollow\">Twitter Web Client</a>","entities":{"hashtags":[],"symbols":[],"user_mentions":[{"name":"Justin 🌙🚀 Herrick","screen_name":"JAH2488","indices":["0","8"],"id_str":"17934912","id":"17934912"}],"urls":[]},"display_text_range":["0","135"],"favorite_count":"2","in_reply_to_status_id_str":"431524570332282880","id_str":"431525330390495232","in_reply_to_user_id":"17934912","truncated":false,"retweet_count":"0","id":"431525330390495232","in_reply_to_status_id":"431524570332282880","created_at":"Thu Feb 06 20:30:30 +0000 2014","favorited":false,"full_text":"@JAH2488 yeah, I would be more OK with apple saying no, if there was a second app market. or even a more casual way to distribute apps.","lang":"en","in_reply_to_screen_name":"JAH2488","in_reply_to_user_id_str":"17934912"},{"retweeted":false,"source":"<a href=\"http://twitter.com\" rel=\"nofollow\">Twitter Web Client</a>","entities":{"hashtags":[],"symbols":[],"user_mentions":[],"urls":[{"url":"http://t.co/UIlu0tjtOS","expanded_url":"http://www.hellonomad.com/products/chargekey-iPhone5","display_url":"hellonomad.com/products/charg…","indices":["39","61"]}]},"display_text_range":["0","61"],"favorite_count":"2","id_str":"436585815586508800","truncated":false,"retweet_count":"0","id":"436585815586508800","possibly_sensitive":false,"created_at":"Thu Feb 20 19:39:04 +0000 2014","favorited":false,"full_text":"Just added a Chargekey to my keychain. http://t.co/UIlu0tjtOS","lang":"en"},{"retweeted":false,"source":"<a href=\"http://twitter.com\" rel=\"nofollow\">Twitter Web Client</a>","entities":{"hashtags":[],"symbols":[],"user_mentions":[],"urls":[]},"display_text_range":["0","123"],"favorite_count":"2","id_str":"435125254822707200","truncated":false,"retweet_count":"0","id":"435125254822707200","created_at":"Sun Feb 16 18:55:19 +0000 2014","favorited":false,"full_text":"Preordering books makes no sense to me in the digital age. They won't sell out. Why not buy it the second you want to read?","lang":"en"},{"retweeted":false,"source":"<a href=\"http://twitter.com\" rel=\"nofollow\">Twitter Web Client</a>","entities":{"hashtags":[],"symbols":[],"user_mentions":[{"name":"tom robinson","screen_name":"tlrobinson","indices":["0","11"],"id_str":"14206068","id":"14206068"}],"urls":[]},"display_text_range":["0","56"],"favorite_count":"2","in_reply_to_status_id_str":"431254810646831104","id_str":"431256300249305089","in_reply_to_user_id":"14206068","truncated":false,"retweet_count":"0","id":"431256300249305089","in_reply_to_status_id":"431254810646831104","created_at":"Thu Feb 06 02:41:28 +0000 2014","favorited":false,"full_text":"@tlrobinson you get a fav for using the word hysteresis.","lang":"en","in_reply_to_screen_name":"tlrobinson","in_reply_to_user_id_str":"14206068"},{"retweeted":false,"source":"<a href=\"http://twitter.com\" rel=\"nofollow\">Twitter Web Client</a>","entities":{"hashtags":[],"symbols":[],"user_mentions":[],"urls":[]},"display_text_range":["0","103"],"favorite_count":"2","id_str":"438362090059751424","truncated":false,"retweet_count":"0","id":"438362090059751424","created_at":"Tue Feb 25 17:17:21 +0000 2014","favorited":false,"full_text":"Are we allowed to tweet funny interactions with app store reviewers, or does that cause a lifetime ban?","lang":"en"},{"retweeted":false,"source":"<a href=\"http://twitter.com\" rel=\"nofollow\">Twitter Web Client</a>","entities":{"hashtags":[],"symbols":[],"user_mentions":[],"urls":[{"url":"http://t.co/XdGdoIdgXG","expanded_url":"http://tcrn.ch/1iytBZZ","display_url":"tcrn.ch/1iytBZZ","indices":["49","71"]}]},"display_text_range":["0","71"],"favorite_count":"2","id_str":"431910785082613760","truncated":false,"retweet_count":"0","id":"431910785082613760","possibly_sensitive":false,"created_at":"Fri Feb 07 22:02:10 +0000 2014","favorited":false,"full_text":"WUT is on your lock screen. (TC care of Kim-Mai) http://t.co/XdGdoIdgXG","lang":"en"},{"retweeted":false,"source":"<a href=\"http://twitter.com\" rel=\"nofollow\">Twitter Web Client</a>","entities":{"hashtags":[],"symbols":[],"user_mentions":[],"urls":[]},"display_text_range":["0","77"],"favorite_count":"1","id_str":"436226839783043072","truncated":false,"retweet_count":"0","id":"436226839783043072","created_at":"Wed Feb 19 19:52:37 +0000 2014","favorited":false,"full_text":"Programming is the closest thing I have to a superpower. Or possibly reading.","lang":"en"},{"retweeted":false,"source":"<a href=\"http://twitter.com\" rel=\"nofollow\">Twitter Web Client</a>","entities":{"hashtags":[],"symbols":[],"user_mentions":[],"urls":[]},"display_text_range":["0","108"],"favorite_count":"1","id_str":"435584154101481472","truncated":false,"retweet_count":"0","id":"435584154101481472","created_at":"Tue Feb 18 01:18:49 +0000 2014","favorited":false,"full_text":"Is knowing who said a quote instead of worrying about the content of a quote just an \"appeal to authority\" ?","lang":"en"},{"retweeted":false,"source":"<a href=\"http://twitter.com\" rel=\"nofollow\">Twitter Web Client</a>","entities":{"hashtags":[],"symbols":[],"user_mentions":[],"urls":[]},"display_text_range":["0","101"],"favorite_count":"1","id_str":"431148002158182400","truncated":false,"retweet_count":"0","id":"431148002158182400","created_at":"Wed Feb 05 19:31:08 +0000 2014","favorited":false,"full_text":"Twitter success message: \"Your Tweet was posted!\" Error message: \"Error creating status.\" CONSISTENCY","lang":"en"},{"coordinates":{"type":"Point","coordinates":["-122.42178888","37.76182067"]},"retweeted":false,"source":"<a href=\"http://twitter.com/download/iphone\" rel=\"nofollow\">Twitter for iPhone</a>","entities":{"hashtags":[],"symbols":[],"user_mentions":[],"urls":[]},"display_text_range":["0","49"],"favorite_count":"1","geo":{"type":"Point","coordinates":["37.76182067","-122.42178888"]},"id_str":"435271642017566722","truncated":false,"retweet_count":"0","id":"435271642017566722","created_at":"Mon Feb 17 04:37:01 +0000 2014","favorited":false,"full_text":"If you could only yolo once? What would you yolo?","lang":"en"},{"retweeted":false,"source":"<a href=\"http://www.apple.com\" rel=\"nofollow\">iOS</a>","entities":{"hashtags":[],"symbols":[],"user_mentions":[],"urls":[{"url":"http://t.co/5tkCd5SRaK","expanded_url":"http://gopop.co/16433","display_url":"gopop.co/16433","indices":["0","22"]}]},"display_text_range":["0","31"],"favorite_count":"1","id_str":"435618621385998336","truncated":false,"retweet_count":"0","id":"435618621385998336","possibly_sensitive":false,"created_at":"Tue Feb 18 03:35:47 +0000 2014","favorited":false,"full_text":"http://t.co/5tkCd5SRaK gunshots","lang":"en"},{"coordinates":{"type":"Point","coordinates":["-122.40724714","37.77979527"]},"retweeted":false,"source":"<a href=\"http://twitter.com/download/iphone\" rel=\"nofollow\">Twitter for iPhone</a>","entities":{"hashtags":[],"symbols":[],"user_mentions":[],"urls":[]},"display_text_range":["0","41"],"favorite_count":"1","geo":{"type":"Point","coordinates":["37.77979527","-122.40724714"]},"id_str":"438027720811765760","truncated":false,"retweet_count":"0","id":"438027720811765760","created_at":"Mon Feb 24 19:08:41 +0000 2014","favorited":false,"full_text":"Two weeks ago the high water mark was 3B.","lang":"en"},{"retweeted":false,"source":"<a href=\"http://twitter.com\" rel=\"nofollow\">Twitter Web Client</a>","entities":{"hashtags":[],"symbols":[],"user_mentions":[],"urls":[]},"display_text_range":["0","98"],"favorite_count":"1","id_str":"438501853735555072","truncated":false,"retweet_count":"1","id":"438501853735555072","created_at":"Wed Feb 26 02:32:43 +0000 2014","favorited":false,"full_text":"I there a way of doing a \"forced credit\" to your debit card without accessing a payment processor?","lang":"en"},{"coordinates":{"type":"Point","coordinates":["-122.39291525","37.77877659"]},"retweeted":false,"source":"<a href=\"http://twitter.com/download/iphone\" rel=\"nofollow\">Twitter for iPhone</a>","entities":{"hashtags":[],"symbols":[],"user_mentions":[],"urls":[]},"display_text_range":["0","75"],"favorite_count":"1","geo":{"type":"Point","coordinates":["37.77877659","-122.39291525"]},"id_str":"433710027241574401","truncated":false,"retweet_count":"0","id":"433710027241574401","created_at":"Wed Feb 12 21:11:43 +0000 2014","favorited":false,"full_text":"Thinking about the breakdown on gender for leads in animated Disney movies.","lang":"en"},{"retweeted":false,"source":"<a href=\"http://twitter.com\" rel=\"nofollow\">Twitter Web Client</a>","entities":{"hashtags":[],"symbols":[],"user_mentions":[],"urls":[]},"display_text_range":["0","43"],"favorite_count":"1","id_str":"436740978582355968","truncated":false,"retweet_count":"0","id":"436740978582355968","created_at":"Fri Feb 21 05:55:38 +0000 2014","favorited":false,"full_text":"Is it too late to try out for the Olympics?","lang":"en"},{"retweeted":false,"source":"<a href=\"http://twitter.com\" rel=\"nofollow\">Twitter Web Client</a>","entities":{"hashtags":[],"symbols":[],"user_mentions":[],"urls":[]},"display_text_range":["0","91"],"favorite_count":"1","id_str":"438364464325201920","truncated":false,"retweet_count":"0","id":"438364464325201920","created_at":"Tue Feb 25 17:26:47 +0000 2014","favorited":false,"full_text":"Security people, what's your OSX/iPhone list? I have littlesnitch, vpn (cloak?), 1password.","lang":"en"},{"retweeted":false,"source":"<a href=\"http://twitter.com/download/iphone\" rel=\"nofollow\">Twitter for iPhone</a>","entities":{"hashtags":[],"symbols":[],"user_mentions":[{"name":"Cameron Walters","screen_name":"ceedub","indices":["0","7"],"id_str":"3922","id":"3922"}],"urls":[]},"display_text_range":["0","27"],"favorite_count":"1","in_reply_to_status_id_str":"436526217441705984","id_str":"436529087478104064","in_reply_to_user_id":"3922","truncated":false,"retweet_count":"0","id":"436529087478104064","in_reply_to_status_id":"436526217441705984","created_at":"Thu Feb 20 15:53:39 +0000 2014","favorited":false,"full_text":"@ceedub everything alright?","lang":"en","in_reply_to_screen_name":"ceedub","in_reply_to_user_id_str":"3922"},{"retweeted":false,"source":"<a href=\"http://twitter.com/download/iphone\" rel=\"nofollow\">Twitter for iPhone</a>","entities":{"hashtags":[],"symbols":[],"user_mentions":[{"name":"Brandon G. Donnelly","screen_name":"donnelly_b","indices":["0","11"],"id_str":"251801850","id":"251801850"}],"urls":[]},"display_text_range":["0","29"],"favorite_count":"1","in_reply_to_status_id_str":"436637490561437696","id_str":"436637682530123776","in_reply_to_user_id":"251801850","truncated":false,"retweet_count":"0","id":"436637682530123776","in_reply_to_status_id":"436637490561437696","created_at":"Thu Feb 20 23:05:10 +0000 2014","favorited":false,"full_text":"@donnelly_b ruins the joke :)","lang":"en","in_reply_to_screen_name":"donnelly_b","in_reply_to_user_id_str":"251801850"},{"retweeted":false,"source":"<a href=\"http://twitter.com\" rel=\"nofollow\">Twitter Web Client</a>","entities":{"user_mentions":[],"urls":[],"symbols":[],"media":[{"expanded_url":"https://twitter.com/pm/status/430233661045096448/photo/1","indices":["72","94"],"url":"http://t.co/S9uJJ39q89","media_url":"http://pbs.twimg.com/media/Bfh_PDmCQAA0fuH.png","id_str":"430233661053485056","id":"430233661053485056","media_url_https":"https://pbs.twimg.com/media/Bfh_PDmCQAA0fuH.png","sizes":{"small":{"w":"490","h":"639","resize":"fit"},"large":{"w":"490","h":"639","resize":"fit"},"medium":{"w":"490","h":"639","resize":"fit"},"thumb":{"w":"150","h":"150","resize":"crop"}},"type":"photo","display_url":"pic.twitter.com/S9uJJ39q89"}],"hashtags":[]},"display_text_range":["0","94"],"favorite_count":"1","id_str":"430233661045096448","truncated":false,"retweet_count":"1","id":"430233661045096448","possibly_sensitive":false,"created_at":"Mon Feb 03 06:57:53 +0000 2014","favorited":false,"full_text":"JCP's tweets were interesting, does this shot look photoshopped to you? http://t.co/S9uJJ39q89","lang":"en","extended_entities":{"media":[{"expanded_url":"https://twitter.com/pm/status/430233661045096448/photo/1","indices":["72","94"],"url":"http://t.co/S9uJJ39q89","media_url":"http://pbs.twimg.com/media/Bfh_PDmCQAA0fuH.png","id_str":"430233661053485056","id":"430233661053485056","media_url_https":"https://pbs.twimg.com/media/Bfh_PDmCQAA0fuH.png","sizes":{"small":{"w":"490","h":"639","resize":"fit"},"large":{"w":"490","h":"639","resize":"fit"},"medium":{"w":"490","h":"639","resize":"fit"},"thumb":{"w":"150","h":"150","resize":"crop"}},"type":"photo","display_url":"pic.twitter.com/S9uJJ39q89"}]}},{"retweeted":false,"source":"<a href=\"http://twitter.com\" rel=\"nofollow\">Twitter Web Client</a>","entities":{"hashtags":[{"text":"kidding","indices":["49","57"]}],"symbols":[],"user_mentions":[],"urls":[]},"display_text_range":["0","57"],"favorite_count":"1","id_str":"432270056727126017","truncated":false,"retweet_count":"0","id":"432270056727126017","created_at":"Sat Feb 08 21:49:47 +0000 2014","favorited":false,"full_text":"This is when I'm supposed to double down, right? #kidding","lang":"en"},{"retweeted":false,"source":"<a href=\"http://twitter.com\" rel=\"nofollow\">Twitter Web Client</a>","entities":{"user_mentions":[],"urls":[],"symbols":[],"media":[{"expanded_url":"https://twitter.com/pm/status/430786743134978048/photo/1","indices":["107","129"],"url":"http://t.co/nZNqmKt4bJ","media_url":"http://pbs.twimg.com/media/Bfp2Qq7CAAATSpd.png","id_str":"430786743139172352","id":"430786743139172352","media_url_https":"https://pbs.twimg.com/media/Bfp2Qq7CAAATSpd.png","sizes":{"small":{"w":"680","h":"282","resize":"fit"},"medium":{"w":"1166","h":"484","resize":"fit"},"large":{"w":"1166","h":"484","resize":"fit"},"thumb":{"w":"150","h":"150","resize":"crop"}},"type":"photo","display_url":"pic.twitter.com/nZNqmKt4bJ"}],"hashtags":[]},"display_text_range":["0","129"],"favorite_count":"1","id_str":"430786743134978048","truncated":false,"retweet_count":"1","id":"430786743134978048","possibly_sensitive":false,"created_at":"Tue Feb 04 19:35:38 +0000 2014","favorited":false,"full_text":"What coffee machines know about us. (likelyhood of someone making coffee given past habits and last drink) http://t.co/nZNqmKt4bJ","lang":"en","extended_entities":{"media":[{"expanded_url":"https://twitter.com/pm/status/430786743134978048/photo/1","indices":["107","129"],"url":"http://t.co/nZNqmKt4bJ","media_url":"http://pbs.twimg.com/media/Bfp2Qq7CAAATSpd.png","id_str":"430786743139172352","id":"430786743139172352","media_url_https":"https://pbs.twimg.com/media/Bfp2Qq7CAAATSpd.png","sizes":{"small":{"w":"680","h":"282","resize":"fit"},"medium":{"w":"1166","h":"484","resize":"fit"},"large":{"w":"1166","h":"484","resize":"fit"},"thumb":{"w":"150","h":"150","resize":"crop"}},"type":"photo","display_url":"pic.twitter.com/nZNqmKt4bJ"}]}},{"retweeted":false,"source":"<a href=\"http://twitter.com\" rel=\"nofollow\">Twitter Web Client</a>","entities":{"user_mentions":[],"urls":[],"symbols":[],"media":[{"expanded_url":"https://twitter.com/pm/status/430746817949487104/photo/1","indices":["54","76"],"url":"http://t.co/jJEyuYwa66","media_url":"http://pbs.twimg.com/media/BfpR8uCCUAAY-_n.png","id_str":"430746817957875712","id":"430746817957875712","media_url_https":"https://pbs.twimg.com/media/BfpR8uCCUAAY-_n.png","sizes":{"small":{"w":"680","h":"517","resize":"fit"},"medium":{"w":"1015","h":"771","resize":"fit"},"thumb":{"w":"150","h":"150","resize":"crop"},"large":{"w":"1015","h":"771","resize":"fit"}},"type":"photo","display_url":"pic.twitter.com/jJEyuYwa66"}],"hashtags":[]},"display_text_range":["0","76"],"favorite_count":"1","id_str":"430746817949487104","truncated":false,"retweet_count":"0","id":"430746817949487104","possibly_sensitive":false,"created_at":"Tue Feb 04 16:56:59 +0000 2014","favorited":false,"full_text":"Rich people don't live in the Mission. Or the Castro? http://t.co/jJEyuYwa66","lang":"en","extended_entities":{"media":[{"expanded_url":"https://twitter.com/pm/status/430746817949487104/photo/1","indices":["54","76"],"url":"http://t.co/jJEyuYwa66","media_url":"http://pbs.twimg.com/media/BfpR8uCCUAAY-_n.png","id_str":"430746817957875712","id":"430746817957875712","media_url_https":"https://pbs.twimg.com/media/BfpR8uCCUAAY-_n.png","sizes":{"small":{"w":"680","h":"517","resize":"fit"},"medium":{"w":"1015","h":"771","resize":"fit"},"thumb":{"w":"150","h":"150","resize":"crop"},"large":{"w":"1015","h":"771","resize":"fit"}},"type":"photo","display_url":"pic.twitter.com/jJEyuYwa66"}]}},{"retweeted":false,"source":"<a href=\"http://twitter.com\" rel=\"nofollow\">Twitter Web Client</a>","entities":{"hashtags":[],"symbols":[],"user_mentions":[],"urls":[{"url":"http://t.co/XqOpEzs0z7","expanded_url":"http://bit.ly/1c8u5qI","display_url":"bit.ly/1c8u5qI","indices":["64","86"]}]},"display_text_range":["0","86"],"favorite_count":"1","id_str":"438725585066405888","truncated":false,"retweet_count":"0","id":"438725585066405888","possibly_sensitive":false,"created_at":"Wed Feb 26 17:21:45 +0000 2014","favorited":false,"full_text":"GIF is a still a popular way to upload a movie to the internet. http://t.co/XqOpEzs0z7","lang":"en"},{"retweeted":false,"source":"<a href=\"http://twitter.com\" rel=\"nofollow\">Twitter Web Client</a>","entities":{"hashtags":[],"symbols":[],"user_mentions":[],"urls":[{"url":"https://t.co/y5DPCs8TBM","expanded_url":"https://itunes.apple.com/us/app/pop/id752511884?mt=8","display_url":"itunes.apple.com/us/app/pop/id7…","indices":["20","43"]}]},"display_text_range":["0","131"],"favorite_count":"1","id_str":"434402150089637888","truncated":false,"retweet_count":"0","id":"434402150089637888","possibly_sensitive":false,"created_at":"Fri Feb 14 19:01:58 +0000 2014","favorited":false,"full_text":"Play with this app: https://t.co/y5DPCs8TBM For people who have trouble expressing themselves with words. &amp;&amp; reaction gifs!","lang":"en"},{"retweeted":false,"source":"<a href=\"http://twitter.com\" rel=\"nofollow\">Twitter Web Client</a>","entities":{"hashtags":[],"symbols":[],"user_mentions":[],"urls":[{"url":"http://t.co/dPouJzYS2H","expanded_url":"http://www.youtube.com/watch?v=V4UWxlVvT1A","display_url":"youtube.com/watch?v=V4UWxl…","indices":["35","57"]}]},"display_text_range":["0","57"],"favorite_count":"1","id_str":"433665532982620160","truncated":false,"retweet_count":"0","id":"433665532982620160","possibly_sensitive":false,"created_at":"Wed Feb 12 18:14:54 +0000 2014","favorited":false,"full_text":"Best role reversal I've seen ever: http://t.co/dPouJzYS2H","lang":"en"},{"retweeted":false,"source":"<a href=\"http://twitter.com\" rel=\"nofollow\">Twitter Web Client</a>","entities":{"hashtags":[],"symbols":[],"user_mentions":[{"name":"Erin McKean","screen_name":"emckean","indices":["0","8"],"id_str":"5380022","id":"5380022"}],"urls":[]},"display_text_range":["0","43"],"favorite_count":"1","in_reply_to_status_id_str":"430069167744491520","id_str":"430070936520253440","in_reply_to_user_id":"5380022","truncated":false,"retweet_count":"0","id":"430070936520253440","in_reply_to_status_id":"430069167744491520","created_at":"Sun Feb 02 20:11:16 +0000 2014","favorited":false,"full_text":"@emckean \"joy of lexicography\" ... awesome!","lang":"en","in_reply_to_screen_name":"emckean","in_reply_to_user_id_str":"5380022"},{"retweeted":false,"source":"<a href=\"http://twitter.com\" rel=\"nofollow\">Twitter Web Client</a>","entities":{"hashtags":[],"symbols":[],"user_mentions":[{"name":"Robert Stephens","screen_name":"rstephens","indices":["0","10"],"id_str":"804376","id":"804376"}],"urls":[{"url":"https://t.co/XacZeBV8gr","expanded_url":"https://www.dogevault.com","display_url":"dogevault.com","indices":["74","97"]}]},"display_text_range":["0","97"],"favorite_count":"1","in_reply_to_status_id_str":"434441245805789184","id_str":"434441482984902656","in_reply_to_user_id":"804376","truncated":false,"retweet_count":"0","id":"434441482984902656","in_reply_to_status_id":"434441245805789184","possibly_sensitive":false,"created_at":"Fri Feb 14 21:38:15 +0000 2014","favorited":false,"full_text":"@rstephens send me your Doge wallet address? You can get a free one here: https://t.co/XacZeBV8gr","lang":"en","in_reply_to_screen_name":"rstephens","in_reply_to_user_id_str":"804376"},{"retweeted":false,"source":"<a href=\"http://twitter.com/download/iphone\" rel=\"nofollow\">Twitter for iPhone</a>","entities":{"hashtags":[],"symbols":[],"user_mentions":[{"name":"Andy Hollandbeck","screen_name":"4ndyman","indices":["0","8"],"id_str":"72650607","id":"72650607"},{"name":"Jack McCloy","screen_name":"JackMcCloy","indices":["9","20"],"id_str":"412858927","id":"412858927"},{"name":"Erin McKean","screen_name":"emckean","indices":["21","29"],"id_str":"5380022","id":"5380022"}],"urls":[]},"display_text_range":["0","106"],"favorite_count":"1","in_reply_to_status_id_str":"437977670060498944","id_str":"437984080575995904","in_reply_to_user_id":"72650607","truncated":false,"retweet_count":"0","id":"437984080575995904","in_reply_to_status_id":"437977670060498944","created_at":"Mon Feb 24 16:15:16 +0000 2014","favorited":false,"full_text":"@4ndyman @JackMcCloy @emckean try google some of the sentences you see today. Not proof but a decent hint.","lang":"en","in_reply_to_screen_name":"4ndyman","in_reply_to_user_id_str":"72650607"},{"retweeted":false,"source":"<a href=\"http://twitter.com\" rel=\"nofollow\">Twitter Web Client</a>","entities":{"hashtags":[],"symbols":[],"user_mentions":[{"name":"Robert Andersen","screen_name":"rsa","indices":["0","4"],"id_str":"6735","id":"6735"}],"urls":[]},"display_text_range":["0","42"],"favorite_count":"1","in_reply_to_status_id_str":"432715468026421248","id_str":"432719986096738304","in_reply_to_user_id":"6735","truncated":false,"retweet_count":"0","id":"432719986096738304","in_reply_to_status_id":"432715468026421248","created_at":"Mon Feb 10 03:37:38 +0000 2014","favorited":false,"full_text":"@rsa man i could use a new coke right now.","lang":"en","in_reply_to_screen_name":"rsa","in_reply_to_user_id_str":"6735"},{"retweeted":false,"source":"<a href=\"http://twitter.com\" rel=\"nofollow\">Twitter Web Client</a>","entities":{"hashtags":[],"symbols":[],"user_mentions":[],"urls":[{"url":"http://t.co/7L9CyQNrw4","expanded_url":"http://flappybirdthinkpieces.tumblr.com/","display_url":"flappybirdthinkpieces.tumblr.com","indices":["60","82"]}]},"display_text_range":["0","82"],"favorite_count":"1","id_str":"436909405569679360","truncated":false,"retweet_count":"0","id":"436909405569679360","possibly_sensitive":false,"created_at":"Fri Feb 21 17:04:54 +0000 2014","favorited":false,"full_text":"People looking deeply in to the meaning behind flappy bird: http://t.co/7L9CyQNrw4","lang":"en"},{"coordinates":{"type":"Point","coordinates":["-122.40620062","37.78439858"]},"retweeted":false,"source":"<a href=\"http://twitter.com/download/iphone\" rel=\"nofollow\">Twitter for iPhone</a>","entities":{"hashtags":[],"symbols":[],"user_mentions":[{"name":"jesseplusplus@mastodon.social","screen_name":"jesseplusplus","indices":["0","14"],"id_str":"24832549","id":"24832549"}],"urls":[]},"display_text_range":["0","61"],"favorite_count":"1","in_reply_to_status_id_str":"432703181466775552","geo":{"type":"Point","coordinates":["37.78439858","-122.40620062"]},"id_str":"436329015033356288","in_reply_to_user_id":"24832549","truncated":false,"retweet_count":"0","id":"436329015033356288","in_reply_to_status_id":"432703181466775552","created_at":"Thu Feb 20 02:38:38 +0000 2014","favorited":false,"full_text":"@jesseplusplus appreciate you posting this. Good read for me.","lang":"en","in_reply_to_screen_name":"jesseplusplus","in_reply_to_user_id_str":"24832549"},{"retweeted":false,"source":"<a href=\"http://twitter.com\" rel=\"nofollow\">Twitter Web Client</a>","entities":{"hashtags":[],"symbols":[],"user_mentions":[{"name":"Avi Bryant","screen_name":"avibryant","indices":["0","10"],"id_str":"13192","id":"13192"}],"urls":[]},"display_text_range":["0","94"],"favorite_count":"1","in_reply_to_status_id_str":"436740755495723008","id_str":"436741175777583104","in_reply_to_user_id":"13192","truncated":false,"retweet_count":"0","id":"436741175777583104","in_reply_to_status_id":"436740755495723008","created_at":"Fri Feb 21 05:56:25 +0000 2014","favorited":false,"full_text":"@avibryant agree. also, when people say the internet is filled with cards, i just see squares.","lang":"en","in_reply_to_screen_name":"avibryant","in_reply_to_user_id_str":"13192"},{"coordinates":{"type":"Point","coordinates":["-122.40033017","37.78488604"]},"retweeted":false,"source":"<a href=\"http://twitter.com/download/iphone\" rel=\"nofollow\">Twitter for iPhone</a>","entities":{"hashtags":[],"symbols":[],"user_mentions":[],"urls":[]},"display_text_range":["0","55"],"favorite_count":"1","geo":{"type":"Point","coordinates":["37.78488604","-122.40033017"]},"id_str":"438542879275765760","truncated":false,"retweet_count":"1","id":"438542879275765760","created_at":"Wed Feb 26 05:15:44 +0000 2014","favorited":false,"full_text":"I actually like jelly and use it. (I'm jelly for jelly)","lang":"en"},{"retweeted":false,"source":"<a href=\"http://twitter.com/download/iphone\" rel=\"nofollow\">Twitter for iPhone</a>","entities":{"hashtags":[],"symbols":[],"user_mentions":[{"name":"Paul Stamatiou 📷","screen_name":"Stammy","indices":["0","7"],"id_str":"624683","id":"624683"},{"name":"dustin curtis","screen_name":"dcurtis","indices":["8","16"],"id_str":"9395832","id":"9395832"}],"urls":[]},"display_text_range":["0","60"],"favorite_count":"1","in_reply_to_status_id_str":"436666817864400896","id_str":"436690713783177216","in_reply_to_user_id":"624683","truncated":false,"retweet_count":"0","id":"436690713783177216","in_reply_to_status_id":"436666817864400896","created_at":"Fri Feb 21 02:35:54 +0000 2014","favorited":false,"full_text":"@Stammy @dcurtis amazon? Is this a new startup I should try?","lang":"en","in_reply_to_screen_name":"Stammy","in_reply_to_user_id_str":"624683"},{"retweeted":false,"source":"<a href=\"http://twitter.com\" rel=\"nofollow\">Twitter Web Client</a>","entities":{"hashtags":[],"symbols":[],"user_mentions":[{"name":"joshua schachter","screen_name":"joshu","indices":["29","35"],"id_str":"5017","id":"5017"}],"urls":[]},"display_text_range":["0","58"],"favorite_count":"1","id_str":"436225906760110080","truncated":false,"retweet_count":"1","id":"436225906760110080","created_at":"Wed Feb 19 19:48:55 +0000 2014","favorited":false,"full_text":"Installing mitmproxy because @joshu has showed me the way.","lang":"en"},{"retweeted":false,"source":"<a href=\"http://twitter.com/download/iphone\" rel=\"nofollow\">Twitter for iPhone</a>","entities":{"hashtags":[],"symbols":[],"user_mentions":[{"name":"Siqi Chen 🧢","screen_name":"blader","indices":["0","7"],"id_str":"4468111","id":"4468111"},{"name":"Andrew Chen","screen_name":"andrewchen","indices":["8","19"],"id_str":"3283901","id":"3283901"}],"urls":[]},"display_text_range":["0","102"],"favorite_count":"1","in_reply_to_status_id_str":"438148658291154944","id_str":"438149211570204672","in_reply_to_user_id":"4468111","truncated":false,"retweet_count":"0","id":"438149211570204672","in_reply_to_status_id":"438148658291154944","created_at":"Tue Feb 25 03:11:27 +0000 2014","favorited":false,"full_text":"@blader @andrewchen I've always thought 'fart app' something you want to use in real life with friends","lang":"en","in_reply_to_screen_name":"blader","in_reply_to_user_id_str":"4468111"},{"coordinates":{"type":"Point","coordinates":["-122.41240306","37.76466512"]},"retweeted":false,"source":"<a href=\"http://twitter.com/download/iphone\" rel=\"nofollow\">Twitter for iPhone</a>","entities":{"hashtags":[],"symbols":[],"user_mentions":[],"urls":[]},"display_text_range":["0","56"],"favorite_count":"1","geo":{"type":"Point","coordinates":["37.76466512","-122.41240306"]},"id_str":"430068052818800641","truncated":false,"retweet_count":"0","id":"430068052818800641","created_at":"Sun Feb 02 19:59:48 +0000 2014","favorited":false,"full_text":"Do any of you sew your own clothes? Please get in touch.","lang":"en"},{"retweeted":false,"source":"<a href=\"http://twitter.com/download/iphone\" rel=\"nofollow\">Twitter for iPhone</a>","entities":{"hashtags":[],"symbols":[],"user_mentions":[{"name":"Garry()","screen_name":"garrytan","indices":["0","9"],"id_str":"11768582","id":"11768582"}],"urls":[]},"display_text_range":["0","48"],"favorite_count":"1","in_reply_to_status_id_str":"434472079702777856","id_str":"434478716291252225","in_reply_to_user_id":"11768582","truncated":false,"retweet_count":"1","id":"434478716291252225","in_reply_to_status_id":"434472079702777856","created_at":"Sat Feb 15 00:06:12 +0000 2014","favorited":false,"full_text":"@garrytan I've been giving out dogecoin all day.","lang":"en","in_reply_to_screen_name":"garrytan","in_reply_to_user_id_str":"11768582"},{"retweeted":false,"source":"<a href=\"http://twitter.com/download/iphone\" rel=\"nofollow\">Twitter for iPhone</a>","entities":{"hashtags":[],"symbols":[],"user_mentions":[{"name":"Jason Waterfalls","screen_name":"splendor","indices":["0","9"],"id_str":"1714161","id":"1714161"}],"urls":[]},"display_text_range":["0","35"],"favorite_count":"1","in_reply_to_status_id_str":"435551312101404672","id_str":"435552949805133824","in_reply_to_user_id":"1714161","truncated":false,"retweet_count":"0","id":"435552949805133824","in_reply_to_status_id":"435551312101404672","created_at":"Mon Feb 17 23:14:50 +0000 2014","favorited":false,"full_text":"@Splendor next thing I want to make","lang":"en","in_reply_to_screen_name":"splendor","in_reply_to_user_id_str":"1714161"},{"retweeted":false,"source":"<a href=\"http://twitter.com\" rel=\"nofollow\">Twitter Web Client</a>","entities":{"hashtags":[],"symbols":[],"user_mentions":[{"name":"Ronen▼.gif","screen_name":"RonenV","indices":["3","10"],"id_str":"1206581","id":"1206581"}],"urls":[]},"display_text_range":["0","56"],"favorite_count":"0","id_str":"437629647472181248","truncated":false,"retweet_count":"0","id":"437629647472181248","created_at":"Sun Feb 23 16:46:53 +0000 2014","favorited":false,"full_text":"RT @RonenV: Apps are to behaviors as books are to ideas.","lang":"en"},{"retweeted":false,"source":"<a href=\"http://twitter.com/download/iphone\" rel=\"nofollow\">Twitter for iPhone</a>","entities":{"hashtags":[],"symbols":[],"user_mentions":[{"name":"Scott Stanfield","screen_name":"seesharp","indices":["3","12"],"id_str":"4085561","id":"4085561"}],"urls":[{"url":"https://t.co/Zzc30RNEGG","expanded_url":"https://github.com/rprieto/tldr","display_url":"github.com/rprieto/tldr","indices":["39","62"]}]},"display_text_range":["0","146"],"favorite_count":"0","id_str":"438928135505969153","truncated":false,"retweet_count":"0","id":"438928135505969153","possibly_sensitive":false,"created_at":"Thu Feb 27 06:46:37 +0000 2014","favorited":false,"full_text":"RT @seesharp: Oh MAN this is awesome: \nhttps://t.co/Zzc30RNEGG\n\n(pun intended)\n\n% man tar   &lt;— too verbose\n% tldr tar     &lt;— simple examples","lang":"en"},{"retweeted":false,"source":"<a href=\"http://twitter.com\" rel=\"nofollow\">Twitter Web Client</a>","entities":{"hashtags":[],"symbols":[],"user_mentions":[{"name":"Erin McKean","screen_name":"emckean","indices":["0","8"],"id_str":"5380022","id":"5380022"}],"urls":[]},"display_text_range":["0","49"],"favorite_count":"0","in_reply_to_status_id_str":"430069167744491520","id_str":"430070237774356481","in_reply_to_user_id":"5380022","truncated":false,"retweet_count":"0","id":"430070237774356481","in_reply_to_status_id":"430069167744491520","created_at":"Sun Feb 02 20:08:29 +0000 2014","favorited":false,"full_text":"@emckean send me an email? my full name at gmail.","lang":"en","in_reply_to_screen_name":"emckean","in_reply_to_user_id_str":"5380022"},{"retweeted":false,"source":"<a href=\"http://twitter.com\" rel=\"nofollow\">Twitter Web Client</a>","entities":{"hashtags":[],"symbols":[],"user_mentions":[{"name":"Eun Ho Lee 이은호 李殷豪","screen_name":"eunho","indices":["0","6"],"id_str":"14528166","id":"14528166"}],"urls":[]},"display_text_range":["0","12"],"favorite_count":"0","in_reply_to_status_id_str":"434483196450045952","id_str":"434554206544883712","in_reply_to_user_id":"14528166","truncated":false,"retweet_count":"0","id":"434554206544883712","in_reply_to_status_id":"434483196450045952","created_at":"Sat Feb 15 05:06:11 +0000 2014","favorited":false,"full_text":"@eunho SENT!","lang":"en","in_reply_to_screen_name":"eunho","in_reply_to_user_id_str":"14528166"},{"retweeted":false,"source":"<a href=\"http://twitter.com\" rel=\"nofollow\">Twitter Web Client</a>","entities":{"hashtags":[],"symbols":[],"user_mentions":[{"name":"Robert Stephens","screen_name":"rstephens","indices":["0","10"],"id_str":"804376","id":"804376"}],"urls":[]},"display_text_range":["0","22"],"favorite_count":"0","in_reply_to_status_id_str":"434455786031304704","id_str":"434456905562353664","in_reply_to_user_id":"804376","truncated":false,"retweet_count":"0","id":"434456905562353664","in_reply_to_status_id":"434455786031304704","created_at":"Fri Feb 14 22:39:32 +0000 2014","favorited":false,"full_text":"@rstephens on the way!","lang":"en","in_reply_to_screen_name":"rstephens","in_reply_to_user_id_str":"804376"},{"retweeted":false,"source":"<a href=\"http://twitter.com/download/iphone\" rel=\"nofollow\">Twitter for iPhone</a>","entities":{"hashtags":[],"symbols":[],"user_mentions":[{"name":"Gary Bernhardt","screen_name":"garybernhardt","indices":["0","14"],"id_str":"809685","id":"809685"}],"urls":[]},"display_text_range":["0","132"],"favorite_count":"0","in_reply_to_status_id_str":"436752645651324930","id_str":"436754189054517248","in_reply_to_user_id":"809685","truncated":false,"retweet_count":"0","id":"436754189054517248","in_reply_to_status_id":"436752645651324930","created_at":"Fri Feb 21 06:48:07 +0000 2014","favorited":false,"full_text":"@garybernhardt (this a joke?) RT/unRT changes your timeline on write. Read timelines are built up on read for viewer. (Last I heard)","lang":"en","in_reply_to_screen_name":"garybernhardt","in_reply_to_user_id_str":"809685"}]