{"retweeted":false,"source":"<a href=\"https://buffer.com\" rel=\"nofollow\">Buffer</a>","entities":{"hashtags":[],"symbols":[],"user_mentions":[],"urls":[]},"display_text_range":["0","119"],"favorite_count":"3","id_str":"166282210096332800","truncated":false,"retweet_count":"4","id":"166282210096332800","created_at":"Sun Feb 05 22:09:02 +0000 2012","favorited":false,"full_text":"It is 2012 and I get irritated whenever people don't 'get' Twitter. It is worst when they are proud of their ignorance.","lang":"en"}