{"retweeted":false,"source":"<a href=\"http://twitter.com\" rel=\"nofollow\">Twitter Web Client</a>","entities":{"hashtags":[],"symbols":[],"user_mentions":[],"urls":[]},"display_text_range":["0","114"],"favorite_count":"0","id_str":"258359149539241984","truncated":false,"retweet_count":"0","id":"258359149539241984","created_at":"Wed Oct 17 00:09:55 +0000 2012","favorited":false,"full_text":"I watching the debates tonight in the mission. If you are interested in joining, hit me up. Shots may be involved.","lang":"en"}