{"retweeted":false,"source":"<a href=\"http://twitter.com\" rel=\"nofollow\">Twitter Web Client</a>","entities":{"hashtags":[],"symbols":[],"user_mentions":[],"urls":[]},"display_text_range":["0","104"],"favorite_count":"3","id_str":"442874438497746944","truncated":false,"retweet_count":"2","id":"442874438497746944","created_at":"Mon Mar 10 04:07:49 +0000 2014","favorited":false,"full_text":"You should spend the next ten minutes pretending to be pablo picasso because it will make you more free.","lang":"en"}