{"retweeted":false,"source":"<a href=\"http://twitter.com/download/iphone\" rel=\"nofollow\">Twitter for iPhone</a>","entities":{"hashtags":[],"symbols":[],"user_mentions":[],"urls":[]},"display_text_range":["0","112"],"favorite_count":"2","id_str":"468592814620565504","truncated":false,"retweet_count":"0","id":"468592814620565504","created_at":"Tue May 20 03:23:27 +0000 2014","favorited":false,"full_text":"\"there are more American men on disability insurance than doing production work in manufacturing.\" Larry summers","lang":"en"}