{"retweeted":false,"source":"<a href=\"http://twitter.com/download/iphone\" rel=\"nofollow\">Twitter for iPhone</a>","entities":{"hashtags":[],"symbols":[],"user_mentions":[{"name":"William Cotton","screen_name":"WilliamCotton","indices":["0","14"],"id_str":"818764912893816832","id":"818764912893816832"}],"urls":[]},"display_text_range":["0","69"],"favorite_count":"0","in_reply_to_status_id_str":"530739343753629696","id_str":"530742714594521088","in_reply_to_user_id":"11745462","truncated":false,"retweet_count":"0","id":"530742714594521088","in_reply_to_status_id":"530739343753629696","created_at":"Fri Nov 07 15:24:58 +0000 2014","favorited":false,"full_text":"@williamcotton maybe three years? Not consistent. Don't use an alarm.","lang":"en","in_reply_to_user_id_str":"11745462"}