{"retweeted":false,"source":"<a href=\"http://twitter.com/download/iphone\" rel=\"nofollow\">Twitter for iPhone</a>","entities":{"hashtags":[],"symbols":[],"user_mentions":[],"urls":[]},"display_text_range":["0","96"],"favorite_count":"1","id_str":"608309315930177536","truncated":false,"retweet_count":"0","id":"608309315930177536","created_at":"Tue Jun 09 16:26:57 +0000 2015","favorited":false,"full_text":"The sooner someone reduces something to cliche, the less comfortable they are using their brain.","lang":"en"}