{"retweeted":false,"source":"<a href=\"http://twitter.com\" rel=\"nofollow\">Twitter Web Client</a>","entities":{"hashtags":[],"symbols":[],"user_mentions":[],"urls":[]},"display_text_range":["0","79"],"favorite_count":"0","in_reply_to_status_id_str":"704016658642411520","id_str":"704020255325073408","in_reply_to_user_id":"1624368620","truncated":false,"retweet_count":"0","id":"704020255325073408","in_reply_to_status_id":"704016658642411520","created_at":"Sun Feb 28 19:08:03 +0000 2016","favorited":false,"full_text":"@steve_wein yeah, i feel like we've been primed and switched over to expect it.","lang":"en","in_reply_to_user_id_str":"1624368620"}