{"retweeted":false,"source":"<a href=\"http://twitter.com\" rel=\"nofollow\">Twitter Web Client</a>","entities":{"hashtags":[],"symbols":[],"user_mentions":[{"name":"Shashank","screen_name":"ItisSG","indices":["0","7"],"id_str":"14196467","id":"14196467"}],"urls":[]},"display_text_range":["0","66"],"favorite_count":"0","in_reply_to_status_id_str":"740957104442363904","id_str":"740958023544250368","in_reply_to_user_id":"14196467","truncated":false,"retweet_count":"0","id":"740958023544250368","in_reply_to_status_id":"740957104442363904","created_at":"Thu Jun 09 17:25:33 +0000 2016","favorited":false,"full_text":"@ItisSG if you read my follow up tweets you'll see i address that.","lang":"en","in_reply_to_screen_name":"ItisSG","in_reply_to_user_id_str":"14196467"}