{"value":{"retweeted":false,"source":"<a href=\"http://twitter.com\" rel=\"nofollow\">Twitter Web Client</a>","entities":{"hashtags":[],"symbols":[],"user_mentions":[],"urls":[]},"display_text_range":["0","94"],"favorite_count":"1","id_str":"742417901253054469","truncated":false,"retweet_count":"0","id":"742417901253054469","created_at":"Mon Jun 13 18:06:35 +0000 2016","favorited":false,"full_text":"apple is doing AI based editing based on the semantic meaning of a word like 'epic' - how cool","lang":"en"}}