{"retweeted":false,"source":"<a href=\"http://twitter.com\" rel=\"nofollow\">Twitter Web Client</a>","entities":{"hashtags":[],"symbols":[],"user_mentions":[{"name":"Micah Cowsik-Herstand","screen_name":"micahherstand","indices":["3","17"],"id_str":"15567045","id":"15567045"}],"urls":[{"url":"https://t.co/bTkkh569tg","expanded_url":"https://twitter.com/pm/status/761625634422464513","display_url":"twitter.com/pm/status/7616…","indices":["65","88"]}]},"display_text_range":["0","88"],"favorite_count":"0","id_str":"763068979862646784","truncated":false,"retweet_count":"0","id":"763068979862646784","possibly_sensitive":false,"created_at":"Tue Aug 09 17:46:36 +0000 2016","favorited":false,"full_text":"RT @micahherstand: Try co-writing a book with other programmers. https://t.co/bTkkh569tg","lang":"en"}