{"retweeted":false,"source":"<a href=\"http://twitter.com\" rel=\"nofollow\">Twitter Web Client</a>","entities":{"hashtags":[],"symbols":[],"user_mentions":[],"urls":[{"url":"https://t.co/bhIRoGoqFf","expanded_url":"http://www.npr.org/sections/health-shots/2016/03/02/468756393/supreme-court-strikes-at-states-efforts-on-health-care-transparency","display_url":"npr.org/sections/healt…","indices":["60","83"]}]},"display_text_range":["0","83"],"favorite_count":"0","id_str":"719587963051466752","truncated":false,"retweet_count":"0","id":"719587963051466752","possibly_sensitive":false,"created_at":"Mon Apr 11 18:08:34 +0000 2016","favorited":false,"full_text":"Health care is going to continue to be confusing and weird: https://t.co/bhIRoGoqFf","lang":"en"}