{"retweeted":false,"source":"<a href=\"http://twitter.com/download/iphone\" rel=\"nofollow\">Twitter for iPhone</a>","entities":{"hashtags":[],"symbols":[],"user_mentions":[{"name":"arram","screen_name":"arram","indices":["0","6"],"id_str":"14779075","id":"14779075"}],"urls":[]},"display_text_range":["0","51"],"favorite_count":"0","in_reply_to_status_id_str":"530503730723291136","id_str":"530504208290942977","in_reply_to_user_id":"14779075","truncated":false,"retweet_count":"0","id":"530504208290942977","in_reply_to_status_id":"530503730723291136","created_at":"Thu Nov 06 23:37:14 +0000 2014","favorited":false,"full_text":"@arram I just started wealth front. This looks good","lang":"en","in_reply_to_screen_name":"arram","in_reply_to_user_id_str":"14779075"}